{
  "date": "2026-04-29",
  "song": "ignition-point",
  "tracks": [
    {
      "artist": "Gesaffelstein",
      "title": "Pursuit",
      "album": "Aleph",
      "year": 2013,
      "search_terms": "gesaffelstein pursuit"
    },
    {
      "artist": "Modeselector",
      "title": "The Black Block",
      "album": "Hello Mom!",
      "year": 2005,
      "search_terms": "modeselector the black block"
    },
    {
      "artist": "Nine Inch Nails",
      "title": "The Becoming",
      "album": "The Downward Spiral",
      "year": 1994,
      "search_terms": "nine inch nails the becoming"
    },
    {
      "artist": "Boys Noize",
      "title": "Overthrow",
      "album": "Mayday",
      "year": 2016,
      "search_terms": "boys noize overthrow"
    },
    {
      "artist": "One Day as a Lion",
      "title": "Wild International",
      "album": "One Day as a Lion",
      "year": 2008,
      "search_terms": "one day as a lion wild international"
    }
  ]
}